Cordic_Test_tb.v
`timescale 1 ps/ 1 ps

module Cordic_Test_tb;

// Inputs
reg 							CLK_50M;
reg 							RST_N;
reg  			[15:0] 		cnt;
reg  			[15:0] 		cnt_n;
reg  			[31:0] 		Phase;
reg  			[31:0] 		Phase_n;
wire 	 		[31:0] 		Sin;
wire 	 		[31:0] 		Cos;
wire 	 		[31:0] 		Error;


// Instantiate the Unit Under Test (UUT)
Cordic_Test 				uut 
(
	.CLK_50M					(CLK_50M		),
	.RST_N					(RST_N		),
	.Phase					(Phase		),
	.Sin						(Sin			),
	.Cos						(Cos			),
	.Error					(Error		)
);

initial
begin
	$dumpfile("Cordic_Test_tb.vcd");
    $dumpvars(0,Cordic_Test_tb);
    $display("Cordic_Test_tb!");
	#0 CLK_50M = 1'b0;
	#10000 RST_N = 1'b0;
	#10000 RST_N = 1'b1;
	//#10000000 $stop;
	
    #10000000 $finish;
end 

always #10000 
begin
	CLK_50M = ~CLK_50M;
end

always @ (posedge CLK_50M or negedge RST_N)
begin
	if(!RST_N)
		cnt <= 1'b0;
	else
		cnt <= cnt_n;
end

always @ (*)
begin
	if(cnt == 16'd359)
		cnt_n = 1'b0;
	else
		cnt_n = cnt + 1'b1;
end

//生成相位,Phase[17:16]为相位的象限,Phase[15:10]为相位的值
always @ (posedge CLK_50M or negedge RST_N)
begin
	if(!RST_N)
		Phase <= 1'b0;
	else
		Phase <= Phase_n;
end

always @ (*)
begin
	if(cnt <= 16'd90)
		Phase_n = cnt;
	else if(cnt > 16'd90 && cnt <= 16'd180)
		Phase_n = {2'd01,cnt - 16'd90};
	else if(cnt > 16'd180 && cnt <= 16'd270)
		Phase_n = {2'd10,cnt - 16'd180};
	else if(cnt > 16'd270)
		Phase_n = {2'd11,cnt - 16'd270};
end

endmodule




module Cordic_Test
(
	CLK_50M,RST_N,
	Phase,
	Sin,Cos,Error
);

input 						CLK_50M;
input 						RST_N;
input 		[31:0] 		Phase;
output		[31:0] 		Sin;
output		[31:0] 		Cos;
output		[31:0] 		Error;

`define rot0  32'd2949120    	//45бу*2^16
`define rot1  32'd1740992    	//26.5651бу*2^16
`define rot2  32'd919872    	//14.0362бу*2^16
`define rot3  32'd466944    	//7.1250бу*2^16
`define rot4  32'd234368    	//3.5763бу*2^16
`define rot5  32'd117312    	//1.7899бу*2^16
`define rot6  32'd58688    	//0.8952бу*2^16
`define rot7  32'd29312    	//0.4476бу*2^16
`define rot8  32'd14656    	//0.2238бу*2^16
`define rot9  32'd7360    		//0.1119бу*2^16
`define rot10 32'd3648    		//0.0560бу*2^16
`define rot11 32'd1856			//0.0280бу*2^16
`define rot12 32'd896    		//0.0140бу*2^16
`define rot13 32'd448    		//0.0070бу*2^16
`define rot14 32'd256    		//0.0035бу*2^16
`define rot15 32'd128    		//0.0018бу*2^16

parameter Pipeline = 16;
parameter K = 32'h09b74;	//K=0.607253*2^16,32'h09b74,

reg signed 	[31:0] 		Sin;
reg signed 	[31:0] 		Cos;
reg signed 	[31:0] 		Error;
reg signed 	[31:0] 		x0=0,y0=0,z0=0;
reg signed 	[31:0] 		x1=0,y1=0,z1=0;
reg signed 	[31:0] 		x2=0,y2=0,z2=0;
reg signed 	[31:0] 		x3=0,y3=0,z3=0;
reg signed 	[31:0] 		x4=0,y4=0,z4=0;
reg signed 	[31:0] 		x5=0,y5=0,z5=0;
reg signed 	[31:0] 		x6=0,y6=0,z6=0;
reg signed 	[31:0] 		x7=0,y7=0,z7=0;
reg signed 	[31:0] 		x8=0,y8=0,z8=0;
reg signed 	[31:0] 		x9=0,y9=0,z9=0;
reg signed 	[31:0] 		x10=0,y10=0,z10=0;
reg signed 	[31:0] 		x11=0,y11=0,z11=0;
reg signed 	[31:0] 		x12=0,y12=0,z12=0;
reg signed 	[31:0] 		x13=0,y13=0,z13=0;
reg signed 	[31:0] 		x14=0,y14=0,z14=0;
reg signed 	[31:0] 		x15=0,y15=0,z15=0;
reg signed 	[31:0] 		x16=0,y16=0,z16=0;
reg 			[ 1:0] 		Quadrant [Pipeline:0];

always @ (posedge CLK_50M or negedge RST_N)
begin
	if(!RST_N)
	begin
		x0 <= 1'b0; 						
		y0 <= 1'b0;
		z0 <= 1'b0;
	end
	else
	begin
		x0 <= K;
		y0 <= 32'd0;
		z0 <= Phase[15:0] << 16;
	end
end

always @ (posedge CLK_50M or negedge RST_N)
begin
	if(!RST_N)
	begin
		x1 <= 1'b0; 						
		y1 <= 1'b0;
		z1 <= 1'b0;
	end
	else if(z0[31])
	begin
      x1 <= x0 + y0;
      y1 <= y0 - x0;
      z1 <= z0 + `rot0;
	end
	else
	begin
      x1 <= x0 - y0;
      y1 <= y0 + x0;
      z1 <= z0 - `rot0;
	end
end

always @ (posedge CLK_50M or negedge RST_N)
begin
	if(!RST_N)
	begin
		x2 <= 1'b0; 						
		y2 <= 1'b0;
		z2 <= 1'b0;
	end
	else if(z1[31])
   begin
        x2 <= x1 + (y1 >>> 1);
        y2 <= y1 - (x1 >>> 1);
        z2 <= z1 + `rot1;
   end
   else
   begin
       x2 <= x1 - (y1 >>> 1);
       y2 <= y1 + (x1 >>> 1);
       z2 <= z1 - `rot1;
   end
end

always @ (posedge CLK_50M or negedge RST_N)
begin
	if(!RST_N)
	begin
		x3 <= 1'b0; 						
		y3 <= 1'b0;
		z3 <= 1'b0;
	end
	else if(z2[31])
   begin
       x3 <= x2 + (y2 >>> 2);
       y3 <= y2 - (x2 >>> 2);
       z3 <= z2 + `rot2;
   end
   else
   begin
       x3 <= x2 - (y2 >>> 2);
       y3 <= y2 + (x2 >>> 2);
       z3 <= z2 - `rot2;
   end
end

always @ (posedge CLK_50M or negedge RST_N)
begin
	if(!RST_N)
	begin
		x4 <= 1'b0; 						
		y4 <= 1'b0;
		z4 <= 1'b0;
	end
	else if(z3[31])
   begin
       x4 <= x3 + (y3 >>> 3);
       y4 <= y3 - (x3 >>> 3);
       z4 <= z3 + `rot3;
   end
   else
   begin
       x4 <= x3 - (y3 >>> 3);
       y4 <= y3 + (x3 >>> 3);
       z4 <= z3 - `rot3;
   end
end

always @ (posedge CLK_50M or negedge RST_N)
begin
	if(!RST_N)
	begin
		x5 <= 1'b0; 						
		y5 <= 1'b0;
		z5 <= 1'b0;
	end
	else if(z4[31])
   begin
       x5 <= x4 + (y4 >>> 4);
       y5 <= y4 - (x4 >>> 4);
       z5 <= z4 + `rot4;
   end
   else
   begin
       x5 <= x4 - (y4 >>> 4);
       y5 <= y4 + (x4 >>> 4);
       z5 <= z4 - `rot4;
   end
end

always @ (posedge CLK_50M or negedge RST_N)
begin
	if(!RST_N)
	begin
		x6 <= 1'b0; 						
		y6 <= 1'b0;
		z6 <= 1'b0;
	end
	else if(z5[31])
   begin
       x6 <= x5 + (y5 >>> 5);
       y6 <= y5 - (x5 >>> 5);
       z6 <= z5 + `rot5;
   end
   else
   begin
       x6 <= x5 - (y5 >>> 5);
       y6 <= y5 + (x5 >>> 5);
       z6 <= z5 - `rot5;
   end
end

always @ (posedge CLK_50M or negedge RST_N)
begin
	if(!RST_N)
	begin
		x7 <= 1'b0; 						
		y7 <= 1'b0;
		z7 <= 1'b0;
	end
	else if(z6[31])
   begin
       x7 <= x6 + (y6 >>> 6);
       y7 <= y6 - (x6 >>> 6);
       z7 <= z6 + `rot6;
   end
   else
   begin
       x7 <= x6 - (y6 >>> 6);
       y7 <= y6 + (x6 >>> 6);
       z7 <= z6 - `rot6;
   end
end

always @ (posedge CLK_50M or negedge RST_N)
begin
	if(!RST_N)
	begin
		x8 <= 1'b0; 						
		y8 <= 1'b0;
		z8 <= 1'b0;
	end
	else if(z7[31])
   begin
       x8 <= x7 + (y7 >>> 7);
       y8 <= y7 - (x7 >>> 7);
       z8 <= z7 + `rot7;
   end
   else
   begin
       x8 <= x7 - (y7 >>> 7);
       y8 <= y7 + (x7 >>> 7);
       z8 <= z7 - `rot7;
   end
end

always @ (posedge CLK_50M or negedge RST_N)
begin
	if(!RST_N)
	begin
		x9 <= 1'b0; 						
		y9 <= 1'b0;
		z9 <= 1'b0;
	end
	else if(z8[31])
   begin
       x9 <= x8 + (y8 >>> 8);
       y9 <= y8 - (x8 >>> 8);
       z9 <= z8 + `rot8;
   end
   else
   begin
       x9 <= x8 - (y8 >>> 8);
       y9 <= y8 + (x8 >>> 8);
       z9 <= z8 - `rot8;
   end
end

always @ (posedge CLK_50M or negedge RST_N)
begin
	if(!RST_N)
	begin
		x10 <= 1'b0; 						
		y10 <= 1'b0;
		z10 <= 1'b0;
	end
	else if(z9[31])
   begin
       x10 <= x9 + (y9 >>> 9);
       y10 <= y9 - (x9 >>> 9);
       z10 <= z9 + `rot9;
   end
   else
   begin
       x10 <= x9 - (y9 >>> 9);
       y10 <= y9 + (x9 >>> 9);
       z10 <= z9 - `rot9;
   end
end

always @ (posedge CLK_50M or negedge RST_N)
begin
	if(!RST_N)
	begin
		x11 <= 1'b0; 						
		y11 <= 1'b0;
		z11 <= 1'b0;
	end
	else if(z10[31])
   begin
       x11 <= x10 + (y10 >>> 10);
       y11 <= y10 - (x10 >>> 10);
       z11 <= z10 + `rot10;
   end
   else
   begin
       x11 <= x10 - (y10 >>> 10);
       y11 <= y10 + (x10 >>> 10);
       z11 <= z10 - `rot10;
   end
end

always @ (posedge CLK_50M or negedge RST_N)
begin
	if(!RST_N)
	begin
		x12 <= 1'b0; 						
		y12 <= 1'b0;
		z12 <= 1'b0;
	end
	else if(z11[31])
   begin
       x12 <= x11 + (y11 >>> 11);
       y12 <= y11 - (x11 >>> 11);
       z12 <= z11 + `rot11;
   end
   else
   begin
       x12 <= x11 - (y11 >>> 11);
       y12 <= y11 + (x11 >>> 11);
       z12 <= z11 - `rot11;
   end
end

always @ (posedge CLK_50M or negedge RST_N)
begin
	if(!RST_N)
	begin
		x13 <= 1'b0; 						
		y13 <= 1'b0;
		z13 <= 1'b0;
	end
	else if(z12[31])
   begin
       x13 <= x12 + (y12 >>> 12);
       y13 <= y12 - (x12 >>> 12);
       z13 <= z12 + `rot12;
   end
   else
   begin
       x13 <= x12 - (y12 >>> 12);
       y13 <= y12 + (x12 >>> 12);
       z13 <= z12 - `rot12;
   end
end

always @ (posedge CLK_50M or negedge RST_N)
begin
	if(!RST_N)
	begin
		x14 <= 1'b0; 						
		y14 <= 1'b0;
		z14 <= 1'b0;
	end
	else if(z13[31])
   begin
       x14 <= x13 + (y13 >>> 13);
       y14 <= y13 - (x13 >>> 13);
       z14 <= z13 + `rot13;
   end
   else
   begin
       x14 <= x13 - (y13 >>> 13);
       y14 <= y13 + (x13 >>> 13);
       z14 <= z13 - `rot13;
   end
end

always @ (posedge CLK_50M or negedge RST_N)
begin
	if(!RST_N)
	begin
		x15 <= 1'b0; 						
		y15 <= 1'b0;
		z15 <= 1'b0;
	end
	else if(z14[31])
   begin
       x15 <= x14 + (y14 >>> 14);
       y15 <= y14 - (x14 >>> 14);
       z15 <= z14 + `rot14;
   end
   else
   begin
       x15 <= x14 - (y14 >>> 14);
       y15 <= y14 + (x14 >>> 14);
       z15 <= z14 - `rot14;
   end
end

always @ (posedge CLK_50M or negedge RST_N)
begin
	if(!RST_N)
	begin
		x16 <= 1'b0; 						
		y16 <= 1'b0;
		z16 <= 1'b0;
	end
	else if(z15[31])
   begin
       x16 <= x15 + (y15 >>> 15);
       y16 <= y15 - (x15 >>> 15);
       z16 <= z15 + `rot15;
   end
   else
   begin
       x16 <= x15 - (y15 >>> 15);
       y16 <= y15 + (x15 >>> 15);
       z16 <= z15 - `rot15;
   end
end

always @ (posedge CLK_50M or negedge RST_N)
begin
	if(!RST_N)
	begin
		Quadrant[0] <= 1'b0;
		Quadrant[1] <= 1'b0;
		Quadrant[2] <= 1'b0;
		Quadrant[3] <= 1'b0;
		Quadrant[4] <= 1'b0;
		Quadrant[5] <= 1'b0;
		Quadrant[6] <= 1'b0;
		Quadrant[7] <= 1'b0;
		Quadrant[8] <= 1'b0;
		Quadrant[9] <= 1'b0;
		Quadrant[10] <= 1'b0;
		Quadrant[11] <= 1'b0;
		Quadrant[12] <= 1'b0;
		Quadrant[13] <= 1'b0;
		Quadrant[14] <= 1'b0;
		Quadrant[15] <= 1'b0;
		Quadrant[16] <= 1'b0;
	end
	else
	begin
		Quadrant[0] <= Phase[17:16];
		Quadrant[1] <= Quadrant[0];
		Quadrant[2] <= Quadrant[1];
		Quadrant[3] <= Quadrant[2];
		Quadrant[4] <= Quadrant[3];
		Quadrant[5] <= Quadrant[4];
		Quadrant[6] <= Quadrant[5];
		Quadrant[7] <= Quadrant[6];
		Quadrant[8] <= Quadrant[7];
		Quadrant[9] <= Quadrant[8];
		Quadrant[10] <= Quadrant[9];
		Quadrant[11] <= Quadrant[10];
		Quadrant[12] <= Quadrant[11];
		Quadrant[13] <= Quadrant[12];
		Quadrant[14] <= Quadrant[13];
		Quadrant[15] <= Quadrant[14];
		Quadrant[16] <= Quadrant[15];
	end
end

always @ (posedge CLK_50M or negedge RST_N)
begin
	if(!RST_N)
	begin
		Cos <= 1'b0;
		Sin <= 1'b0;
		Error <= 1'b0;
	end
	else
	begin
		Error <= z16;
		case(Quadrant[16])
			2'b00: //if the Phase is in first Quadrant,the Sin(X)=Sin(A),Cos(X)=Cos(A)
				begin
					Cos <= x16;
					Sin <= y16;
				end
			2'b01: //if the Phase is in second Quadrant,the Sin(X)=Sin(A+90)=CosA,Cos(X)=Cos(A+90)=-SinA
				begin
					Cos <= ~(y16) + 1'b1;//-Sin
					Sin <= x16;//Cos
				end
			2'b10: //if the Phase is in third Quadrant,the Sin(X)=Sin(A+180)=-SinA,Cos(X)=Cos(A+180)=-CosA
				begin
					Cos <= ~(x16) + 1'b1;//-Cos
					Sin <= ~(y16) + 1'b1;//-Sin
				end
			2'b11: //if the Phase is in forth Quadrant,the Sin(X)=Sin(A+270)=-CosA,Cos(X)=Cos(A+270)=SinA
				begin
					Cos <= y16;//Sin
					Sin <= ~(x16) + 1'b1;//-Cos
				end
		endcase
	end
end

endmodule

Cordic_Test_tb.vcd
$date
	Fri Jan 03 18:15:22 2020
$end
$version
	Icarus Verilog
$end
$timescale
	1ps
$end
$scope module Cordic_Test_tb $end
$var wire 32 ! Sin [31:0] $end
$var wire 32 " Error [31:0] $end
$var wire 32 # Cos [31:0] $end
$var reg 1 $ CLK_50M $end
$var reg 32 % Phase [31:0] $end
$var reg 32 & Phase_n [31:0] $end
$var reg 1 ' RST_N $end
$var reg 16 ( cnt [15:0] $end
$var reg 16 ) cnt_n [15:0] $end
$scope module uut $end
$var wire 1 $ CLK_50M $end
$var wire 32 * Phase [31:0] $end
$var wire 1 ' RST_N $end
$var reg 32 + Cos [31:0] $end
$var reg 32 , Error [31:0] $end
$var reg 32 - Sin [31:0] $end
$var reg 32 . x0 [31:0] $end
$var reg 32 / x1 [31:0] $end
$var reg 32 0 x10 [31:0] $end
$var reg 32 1 x11 [31:0] $end
$var reg 32 2 x12 [31:0] $end
$var reg 32 3 x13 [31:0] $end
$var reg 32 4 x14 [31:0] $end
$var reg 32 5 x15 [31:0] $end
$var reg 32 6 x16 [31:0] $end
$var reg 32 7 x2 [31:0] $end
$var reg 32 8 x3 [31:0] $end
$var reg 32 9 x4 [31:0] $end
$var reg 32 : x5 [31:0] $end
$var reg 32 ; x6 [31:0] $end
$var reg 32 < x7 [31:0] $end
$var reg 32 = x8 [31:0] $end
$var reg 32 > x9 [31:0] $end
$var reg 32 ? y0 [31:0] $end
$var reg 32 @ y1 [31:0] $end
$var reg 32 A y10 [31:0] $end
$var reg 32 B y11 [31:0] $end
$var reg 32 C y12 [31:0] $end
$var reg 32 D y13 [31:0] $end
$var reg 32 E y14 [31:0] $end
$var reg 32 F y15 [31:0] $end
$var reg 32 G y16 [31:0] $end
$var reg 32 H y2 [31:0] $end
$var reg 32 I y3 [31:0] $end
$var reg 32 J y4 [31:0] $end
$var reg 32 K y5 [31:0] $end
$var reg 32 L y6 [31:0] $end
$var reg 32 M y7 [31:0] $end
$var reg 32 N y8 [31:0] $end
$var reg 32 O y9 [31:0] $end
$var reg 32 P z0 [31:0] $end
$var reg 32 Q z1 [31:0] $end
$var reg 32 R z10 [31:0] $end
$var reg 32 S z11 [31:0] $end
$var reg 32 T z12 [31:0] $end
$var reg 32 U z13 [31:0] $end
$var reg 32 V z14 [31:0] $end
$var reg 32 W z15 [31:0] $end
$var reg 32 X z16 [31:0] $end
$var reg 32 Y z2 [31:0] $end
$var reg 32 Z z3 [31:0] $end
$var reg 32 [ z4 [31:0] $end
$var reg 32 \ z5 [31:0] $end
$var reg 32 ] z6 [31:0] $end
$var reg 32 ^ z7 [31:0] $end
$var reg 32 _ z8 [31:0] $end
$var reg 32 ` z9 [31:0] $end
$upscope $end
$upscope $end
$enddefinitions $end
#0
$dumpvars
b0 `
b0 _
b0 ^
b0 ]
b0 \
b0 [
b0 Z
b0 Y
b0 X
b0 W
b0 V
b0 U
b0 T
b0 S
b0 R
b0 Q
b0 P
b0 O
b0 N
b0 M
b0 L
b0 K
b0 J
b0 I
b0 H
b0 G
b0 F
b0 E
b0 D
b0 C
b0 B
b0 A
b0 @
b0 ?
b0 >
b0 =
b0 <
b0 ;
b0 :
b0 9
b0 8
b0 7
b0 6
b0 5
b0 4
b0 3
b0 2
b0 1
b0 0
b0 /
b0 .
bx -
bx ,
bx +
bx *
bx )
bx (
x'
bx &
bx %
0$
bx #
bx "
bx !
$end
#10000
b0 &
b1 )
b0 "
b0 ,
b0 !
b0 -
b0 #
b0 +
b0 (
b0 %
b0 *
0'
1$
#20000
1'
0$
#30000
b10 )
b1 &
b1 (
b11111111111111111111111110000000 X
b11111111111111111111111100000000 W
b11111111111111111111111001000000 V
b11111111111111111111110010000000 U
b11111111111111111111100011000000 T
b11111111111111111111000111000000 S
b11111111111111111110001101000000 R
b11111111111111111100011011000000 `
b11111111111111111000110110000000 _
b11111111111111110001101011000000 ^
b11111111111111100011010111000000 ]
b11111111111111000110110010000000 \
b11111111111110001110000000000000 [
b11111111111100011111011011000000 Z
b11111111111001010110111101000000 Y
b11111111110100110000000000000000 Q
b1001101101110100 .
1$
#40000
0$
#50000
b10 &
b11 )
b1001101101110100 @
b1001101101110100 /
b11111111111011011001000011000000 Y
b11111111111100110111100010000000 Z
b11111111111110010001011011000000 [
b11111111111111000111001110000000 \
b11111111111111100011011011000000 ]
b11111111111111110001101100000000 ^
b11111111111111111000110101000000 _
b11111111111111111110001110000000 R
b11111111111111111111000110000000 S
b11111111111111111111100100000000 T
b11111111111111111111110001000000 U
b11111111111111111111111101000000 W
b11111111111111111111111110000000 "
b11111111111111111111111110000000 ,
b10 (
b1 %
b1 *
1$
#60000
0$
#70000
b100 )
b11 &
b10 %
b10 *
b11 (
b11111111111111111111111111000000 X
b11111111111111111111111000000000 V
b11111111111111111111110010000000 U
b11111111111111111111100011000000 T
b11111111111111111111000111000000 S
b11111111111111111100011010000000 `
b11111111111111111000110110000000 _
b11111111111111110001110000000000 ^
b11111111111111100011110111000000 ]
b11111111111111001010101001000000 \
b11111111111110101001100010000000 [
b11111111111110111001101000000000 Z
b100110110111010 H
b1110100100101110 7
b10000000000000000 P
1$
#80000
0$
#90000
b100 &
b101 )
b100000000000000000 P
b11111111110101000000000000000000 Q
b1001101101111 I
b1111110010011100 8
b101011101000000000 [
b11111111111111100010110000000000 \
b11111111111111100111010010000000 ]
b11111111111111110010001100000000 ^
b11111111111111111000111010000000 _
b11111111111111111100011011000000 `
b11111111111111111110001101000000 R
b11111111111111111111100100000000 T
b11111111111111111111110001000000 U
b11111111111111111111111001000000 V
b11111111111111111111111100000000 W
b11111111111111111111111111000000 "
b11111111111111111111111111000000 ,
b100 (
b11 %
b11 *
1$
#100000
0$
#110000
b110 )
b101 &
b100 %
b100 *
b101 (
b11111111111111111111111110000000 X
b11111111111111111111111101000000 W
b11111111111111111111111000000000 V
b11111111111111111111110010000000 U
b11111111111111111111000110000000 S
b11111111111111111110001110000000 R
b11111111111111111100011111000000 `
b11111111111111111001010110000000 _
b11111111111111110101100111000000 ^
b11111111111111111111011001000000 ]
b11111111111111110010011010000000 \
b11111111111111111111001111011100 J
b1111111100001001 9
b11111111111011101001000011000000 Y
b11111111110101010000000000000000 Q
b110000000000000000 P
1$
#120000
0$
#130000
b110 &
b111 )
b1000000000000000000 P
b11111111110101100000000000000000 Q
b11111111111011111001000011000000 Y
b11111111111111001001101000000000 Z
b1111001100 K
b1111111111001100 :
b1111000011000000 ]
b1101101110000000 ^
b11111111111111111100110001000000 _
b11111111111111111100111011000000 `
b11111111111111111110010010000000 R
b11111111111111111111000111000000 S
b11111111111111111111100011000000 T
b11111111111111111111111001000000 V
b11111111111111111111111100000000 W
b11111111111111111111111111000000 X
b11111111111111111111111110000000 "
b11111111111111111111111110000000 ,
b110 (
b101 %
b101 *
1$
#140000
0$
#150000
b1000 )
b111 &
b110 %
b110 *
b111 (
b11111111111111111111111111000000 "
b11111111111111111111111111000000 ,
b11111111111111111111111110000000 X
b11111111111111111111111101000000 W
b11111111111111111111110001000000 U
b11111111111111111111100100000000 T
b11111111111111111111001011000000 S
b11111111111111111110101110000000 R
b10110000000 `
b110100100000000 _
b101110000000 ^
b11111111111111111111101111001110 L
b1111111111101010 ;
b111011101000000000 [
b11111111111111011001101000000000 Z
b11111111111100001001000011000000 Y
b11111111110101110000000000000000 Q
b1010000000000000000 P
1$
#160000
0$
#170000
b1000 &
b1001 )
b1100000000000000000 P
b11111111110110000000000000000000 Q
b11111111111100011001000011000000 Y
b11111111111111101001101000000000 Z
b1001011101000000000 [
b10011010000000 \
b11111111111111111111111111001101 M
b1111111111111011 <
b11111111111111111001100100000000 _
b10111111000000 `
b11111111111111111110100011000000 R
b11111111111111111111100111000000 S
b11111111111111111111101000000000 T
b11111111111111111111110010000000 U
b11111111111111111111111000000000 V
b11111111111111111111111111000000 X
b11111111111111111111111110000000 "
b11111111111111111111111110000000 ,
b1000 (
b111 %
b111 *
1$
#180000
0$
#190000
b1010 )
b1001 &
b1000 %
b1000 *
b1001 (
b11111111111111111111111111000000 "
b11111111111111111111111111000000 ,
b11111111111111111111111100000000 W
b11111111111111111111111001000000 V
b11111111111111111111110110000000 U
b100000000 T
b11111111111111111111011100000000 S
b1001100000000 R
b11111111111111111101001001000000 `
b111001100 N
b1111111111111100 =
b11111111111111100101110001000000 ]
b101111001010 L
b1111111110101110 ;
b10010011010000000 \
b1011011101000000000 [
b11111111111111111001101000000000 Z
b11111111111100101001000011000000 Y
b11111111110110010000000000000000 Q
b1110000000000000000 P
1$
#200000
0$
#210000
b1010 &
b1011 )
b10000000000000000000 P
b11111111110110100000000000000000 Q
b11111111111100111001000011000000 Y
b1001101000000000 Z
b1101011101000000000 [
b100010011010000000 \
b11111111111111110101110001000000 ]
b11111111111111110100000110000000 ^
b11111001100 M
b1111111111011101 <
b11001101 O
b1111111111111101 >
b11111111111111111110111100000000 R
b10011000000 S
b11111111111111111111111001000000 T
b11111111111111111111111101000000 V
b11111111111111111111111101000000 W
b11111111111111111111111110000000 X
b1010 (
b1001 %
b1001 *
1$
#220000
0$
#230000
b1100 )
b1011 &
b1010 %
b1010 *
b1011 (
b11111111111111111111111110000000 "
b11111111111111111111111110000000 ,
b11111111111111111111111111000000 X
b1000000 W
b111000000 U
b11111111111111111111110110000000 T
b11111111111111111111110101000000 S
b1001110 A
b1111111111111101 0
b11111111111111111011010000000000 _
b10111001101 N
b1111111111101100 =
b100000110000000 ^
b101110001000000 ]
b110010011010000000 \
b11111111111110010111101000000000 [
b11001100000010 J
b1111101000101111 9
b11001101000000000 Z
b11111111111101001001000011000000 Y
b11111111110110110000000000000000 Q
b10010000000000000000 P
1$
#240000
0$
#250000
b1100 &
b1101 )
b10100000000000000000 P
b11111111110111000000000000000000 Q
b11111111111101011001000011000000 Y
b101001101000000000 Z
b11111111111110100111101000000000 [
b11111111111111010000110110000000 \
b10001101100000 K
b1111110101011111 :
b10101110001000000 ]
b11111111111111110111011100000000 ^
b111111001000 M
b1111111101111111 <
b11111111111111111100111100000000 _
b100111001011 N
b1111111111001110 =
b11111111111111111110110101000000 `
b10011001110 O
b1111111111110001 >
b1111 B
b1111111111111101 1
b10010000000 T
b100000000 U
b0 V
b11111111111111111111111111000000 "
b11111111111111111111111111000000 ,
b1100 (
b1011 %
b1011 *
1$
#260000
0$
#270000
b1110 )
b1101 &
b1100 %
b1100 *
b1101 (
b11111111111111111111111100000000 W
b11111111111111111111111101000000 V
b11111111111111111111111111110000 C
b1111111111111101 2
b101000000000 R
b10001001111 A
b1111111111110011 0
b100001000000 `
b100011001100 O
b1111111111010111 >
b11111111111111111110100110000000 _
b110111001010 N
b1111111110011110 =
b111011100000000 ^
b11111111111111101101011111000000 ]
b1101101110110 L
b1111111001111010 ;
b11111111111111100000110110000000 \
b11111111111110110111101000000000 [
b111001101000000000 Z
b11111111111101101001000011000000 Y
b11111111110111010000000000000000 Q
b10110000000000000000 P
1$
#280000
0$
#290000
b1110 &
b1111 )
b11000000000000000000 P
b11111111110111100000000000000000 Q
b11111111111101111001000011000000 Y
b1001001101000000000 Z
b11111111111111000111101000000000 [
b11111111111111110000110110000000 \
b11111111111111111101011111000000 ]
b11111111111111111011110100000000 ^
b1011101111101 M
b1111111011100111 <
b10010000000 _
b1000111000110 N
b1111111101100000 =
b10001011000000 `
b110011001011 O
b1111111110101011 >
b11111111111111111110101110000000 R
b100101001011 A
b1111111111010011 0
b11111111111111111111101111000000 S
b10010001110 B
b1111111111110010 1
b11111111111111111111111111111111 D
b1111111111111110 3
b1000000 W
b11111111111111111111111110000000 X
b1110 (
b1101 %
b1101 *
1$
#300000
0$
#310000
b10000 )
b1111 &
b1110 %
b1110 *
b1111 (
b11111111111111111111111110000000 "
b11111111111111111111111110000000 ,
b11111111111111111111111111000000 X
b110 E
b1111111111111111 4
b1100000000 T
b10001101111 C
b1111111111110010 2
b11111111111111111111100111000000 S
b100100001100 B
b1111111111010101 1
b11000000000 R
b110101001010 A
b1111111110100101 0
b11111111111111111100101101000000 `
b1001011000101 O
b1111111101001111 >
b10111110000000 _
b1010110000000 N
b1111111100010101 =
b1011110100000000 ^
b1101011111000000 ]
b110110000000 \
b11111111111111010111101000000000 [
b1011001101000000000 Z
b11111111111110001001000011000000 Y
b11111111110111110000000000000000 Q
b11010000000000000000 P
1$
#320000
0$
#330000
b10000 &
b10001 )
b11100000000000000000 P
b11111111111000000000000000000000 Q
b11111111111110011001000011000000 Y
b1101001101000000000 Z
b11111111111111100111101000000000 [
b10000110110000000 \
b11111111111111100100001101000000 ]
b10101101001010 L
b1111110001000100 ;
b11111111111111111111001010000000 ^
b1111101101111 M
b1111111000001101 <
b100101010000000 _
b1100101111010 N
b1111111010111001 =
b11111111111111111111011001000000 `
b1011001111111 O
b1111111100000000 >
b11111111111111111110100000000000 R
b1001001000110 A
b1111111101011000 0
b11111111111111111111011111000000 S
b110110001001 B
b1111111110100010 1
b100000000 T
b100011101101 C
b1111111111010110 2
b11111111111111111111111110000000 U
b10001111110 D
b1111111111110010 3
b11 F
b1111111111111111 5
b11111111111111111111111111000000 "
b11111111111111111111111111000000 ,
b10000 (
b1111 %
b1111 *
1$
#340000
0$
#350000
b10010 )
b10001 &
b10000 %
b10000 *
b10001 (
b100 G
b1111111111111111 6
b101000000 V
b10001110111 E
b1111111111110010 4
b11111111111111111111110110000000 U
b100011111100 D
b1111111111010110 3
b11111111111111111111111100000000 T
b110101101010 C
b1111111110100011 2
b11111111111111111111011001000000 S
b1001000000111 B
b1111111101011100 1
b1001100000000 R
b1011000000000 A
b1111111100001011 0
b1000101000000 `
b1101001111000 O
b1111111010100000 >
b110010100000000 _
b1110101110011 N
b1111111001001011 =
b11111111111111110010100010000000 ^
b10011101011001 M
b1111110011110001 <
b11111111111111110100001101000000 ]
b100000110110000000 \
b11111111111111110111101000000000 [
b1111001101000000000 Z
b11111111111110101001000011000000 Y
b11111111111000010000000000000000 Q
b11110000000000000000 P
1$
#360000
0$
#370000
b10010 &
b10011 )
b100000000000000000000 P
b11111111111000100000000000000000 Q
b11111111111110111001000011000000 Y
b10001001101000000000 Z
b111101000000000 [
b110000110110000000 \
b100001101000000 ]
b10100010000000 ^
b11111111111111111001101100000000 _
b10010101100000 N
b1111110100111111 =
b10101111000000 `
b1111001110001 O
b1111111000101110 >
b11111111111111111111010010000000 R
b1101011110111 A
b1111111010010011 0
b10011000000 S
b1011000111111 B
b1111111100000110 1
b11111111111111111111110110000000 T
b1000111101000 C
b1111111101011110 2
b1010000000 U
b110101011011 D
b1111111110100011 3
b11111111111111111111111101000000 V
b100011110101 E
b1111111111010110 4
b10001111010 F
b1111111111110010 5
b100 !
b100 -
b1111111111111111 #
b1111111111111111 +
b10010 (
b10001 %
b10001 *
1$
#380000
0$
#390000
b10100 )
b10011 &
b10010 %
b10010 *
b10011 (
b10001111011 G
b1111111111110010 6
b100011110010 F
b1111111111010110 5
b11000000 V
b110101100010 E
b1111111110100011 4
b100000000 U
b1000111011001 D
b1111111101011111 3
b1011001011110 C
b1111111100000100 2
b1011000000 S
b1101010111000 B
b1111111010011001 1
b111100000000 R
b1111011110000 A
b1111111000011111 0
b11111111111111111101010001000000 `
b10010001100011 O
b1111110101100100 >
b11111111111111111011011000000000 _
b10100101010010 N
b1111110010100011 =
b11111111111111110101111000000000 ^
b10111100111011 M
b1111101110010111 <
b10100001101000000 ]
b11111111111111001110011010000000 \
b100001010100100 K
b1111011011111111 :
b10111101000000000 [
b10011001101000000000 Z
b11111111111111001001000011000000 Y
b11111111111000110000000000000000 Q
b100010000000000000000 P
1$
#400000
0$
